setup.py
udctydist/Binomialdistribution.py
udctydist/Gaussiandistribution.py
udctydist/Generaldistribution.py
udctydist/__init__.py
udctydist.egg-info/PKG-INFO
udctydist.egg-info/SOURCES.txt
udctydist.egg-info/dependency_links.txt
udctydist.egg-info/not-zip-safe
udctydist.egg-info/top_level.txt